staff_toolbar/__init__.py
staff_toolbar/appsettings.py
staff_toolbar/conf.py
staff_toolbar/items.py
staff_toolbar/loading.py
staff_toolbar/views.py
staff_toolbar/locale/nl/LC_MESSAGES/django.mo
staff_toolbar/locale/nl/LC_MESSAGES/django.po
staff_toolbar/static/staff_toolbar/staff_toolbar.css
staff_toolbar/templatetags/__init__.py
staff_toolbar/templatetags/staff_toolbar_tags.py
staff_toolbar/tests/__init__.py
staff_toolbar/tests/test_all.py
staff_toolbar/tests/urls.py
django_staff_toolbar-2.0.dist-info/AUTHORS
django_staff_toolbar-2.0.dist-info/LICENSE
django_staff_toolbar-2.0.dist-info/METADATA
django_staff_toolbar-2.0.dist-info/WHEEL
django_staff_toolbar-2.0.dist-info/top_level.txt
django_staff_toolbar-2.0.dist-info/RECORD
